dariko/__init__.py
dariko/config.py
dariko/driver.py
dariko/exceptions.py
dariko/model_utils.py
dariko/models/README.md
dariko/models/__init__.py
dariko/models/claude.py
dariko/models/gemma.py
dariko/models/gpt.py
dariko/models/llm.py
dariko-2.0.0.dist-info/METADATA
dariko-2.0.0.dist-info/WHEEL
dariko-2.0.0.dist-info/licenses/LICENSE
dariko-2.0.0.dist-info/RECORD
