Metadata-Version: 2.4
Name: dariko
Version: 2.0.0
Summary: LLMの出力をPydanticモデルで型安全に扱うためのPythonライブラリ
Project-URL: Homepage, https://github.com/YutoNose/dariko
Project-URL: Repository, https://github.com/YutoNose/dariko.git
Project-URL: Documentation, https://github.com/YutoNose/dariko#readme
Author-email: Yuto Nose <yuto.nose@gmail.com>
License: MIT
License-File: LICENSE
Keywords: gpt,llm,openai,pydantic,type-safety
Classifier: Development Status :: 4 - Beta
Classifier: Intended Audience :: Developers
Classifier: License :: OSI Approved :: MIT License
Classifier: Programming Language :: Python :: 3
Classifier: Programming Language :: Python :: 3.8
Classifier: Programming Language :: Python :: 3.9
Classifier: Programming Language :: Python :: 3.10
Classifier: Programming Language :: Python :: 3.11
Classifier: Programming Language :: Python :: 3.12
Classifier: Topic :: Software Development :: Libraries :: Application Frameworks
Classifier: Topic :: Software Development :: Libraries :: Python Modules
Requires-Python: >=3.8
Requires-Dist: pydantic>=2.0.0
Requires-Dist: requests>=2.31.0
Requires-Dist: torch>=2.0.0
Requires-Dist: transformers>=4.37.0
Provides-Extra: develop
Requires-Dist: dotenv; extra == 'develop'
Requires-Dist: pre-commit; extra == 'develop'
Requires-Dist: pytest; extra == 'develop'
Requires-Dist: ruff; extra == 'develop'
